jtext/__about__.py
jtext/__init__.py
jtext/tools.py
jtext-0.2.0.dist-info/METADATA
jtext-0.2.0.dist-info/WHEEL
jtext-0.2.0.dist-info/licenses/LICENSE
jtext-0.2.0.dist-info/RECORD
